[
  {
    "user": "mah name",
    "text": "hello",
    "timestamp": 1746857725094
  },
  {
    "user": "mah name",
    "text": "test",
    "timestamp": 1746857729059
  },
  {
    "user": "mah name",
    "text": "tst",
    "timestamp": 1746857730856
  },
  {
    "user": "mah name",
    "text": "345345",
    "timestamp": 1746857732198
  },
  {
    "user": "mah name",
    "text": "4564656",
    "timestamp": 1746857733954
  },
  {
    "user": "mah name",
    "text": "64465",
    "timestamp": 1746857735210
  },
  {
    "user": "mah name",
    "text": "2345534",
    "timestamp": 1746857740843
  },
  {
    "user": "mah name",
    "text": "5675",
    "timestamp": 1746857741798
  },
  {
    "user": "mah name",
    "text": "76868",
    "timestamp": 1746857742867
  },
  {
    "user": "mah name",
    "text": "67868",
    "timestamp": 1746857743972
  },
  {
    "user": "mah name",
    "text": "8868",
    "timestamp": 1746857745826
  },
  {
    "user": "mah name",
    "text": "68786867",
    "timestamp": 1746857747933
  },
  {
    "user": "mah name",
    "text": "adadw",
    "timestamp": 1746857812681
  },
  {
    "user": "mah name",
    "text": "test",
    "timestamp": 1746859030617
  },
  {
    "user": "mah name",
    "text": "wdad",
    "timestamp": 1746859145968
  },
  {
    "user": "mah name",
    "text": "wd",
    "timestamp": 1746859150107
  },
  {
    "user": "mah name",
    "text": "dw",
    "timestamp": 1746859153118
  },
  {
    "user": "mah name",
    "text": "test",
    "timestamp": 1746859935852
  },
  {
    "user": "mah name",
    "text": "test",
    "timestamp": 1746860166230
  },
  {
    "user": "mah name",
    "text": "123",
    "timestamp": 1746860168260
  },
  {
    "user": "mah name",
    "text": "009",
    "timestamp": 1746860557110
  },
  {
    "user": "mah name",
    "text": "hm",
    "timestamp": 1746861013912
  },
  {
    "user": "mah name",
    "text": "ads",
    "timestamp": 1746861187761
  },
  {
    "user": "mah name",
    "text": "asdasd",
    "timestamp": 1746861188980
  },
  {
    "user": "mah name",
    "text": "asdasd",
    "timestamp": 1746861189804
  },
  {
    "user": "mah name",
    "text": "ghjk",
    "timestamp": 1746861417061
  },
  {
    "user": "mah name",
    "text": "dsfs",
    "timestamp": 1746861438218
  },
  {
    "user": "mah name",
    "text": "test",
    "timestamp": 1746861849326
  },
  {
    "user": "mah name",
    "text": "efdwf",
    "timestamp": 1746862626468
  },
  {
    "user": "mah name",
    "text": "asdfasfd",
    "timestamp": 1746862628400
  },
  {
    "user": "TinyBitSerious",
    "text": "qwe",
    "timestamp": 1746863049382
  },
  {
    "user": "TinyBitSerious",
    "text": "werwerwer",
    "timestamp": 1746863050924
  },
  {
    "user": "TinyBitSerious",
    "text": "123",
    "timestamp": 1746863969863
  },
  {
    "user": "TinyBitSerious",
    "text": "123",
    "timestamp": 1746863972350
  },
  {
    "user": "TinyBitSerious",
    "text": "123",
    "timestamp": 1746863973064
  },
  {
    "user": "TinyBitSerious",
    "text": "45",
    "timestamp": 1746863975775
  },
  {
    "user": "TinyBitSerious",
    "text": "453",
    "timestamp": 1746863976288
  },
  {
    "user": "TinyBitSerious",
    "text": "46346",
    "timestamp": 1746863976774
  },
  {
    "user": "TinyBitSerious",
    "text": "36",
    "timestamp": 1746863976930
  },
  {
    "user": "TinyBitSerious",
    "text": "3",
    "timestamp": 1746863977085
  },
  {
    "user": "TinyBitSerious",
    "text": "46",
    "timestamp": 1746863977253
  },
  {
    "user": "TinyBitSerious",
    "text": "346",
    "timestamp": 1746863977421
  },
  {
    "user": "TinyBitSerious",
    "text": "3464363262",
    "timestamp": 1746863978208
  },
  {
    "user": "TinyBitSerious",
    "text": "346",
    "timestamp": 1746863978380
  },
  {
    "user": "TinyBitSerious",
    "text": "2346",
    "timestamp": 1746863978584
  },
  {
    "user": "TinyBitSerious",
    "text": "234",
    "timestamp": 1746863978751
  },
  {
    "user": "TinyBitSerious",
    "text": "62",
    "timestamp": 1746863978921
  },
  {
    "user": "TinyBitSerious",
    "text": "36",
    "timestamp": 1746863979084
  },
  {
    "user": "TinyBitSerious",
    "text": "234623",
    "timestamp": 1746863979430
  },
  {
    "user": "TinyBitSerious",
    "text": "46",
    "timestamp": 1746863979615
  },
  {
    "user": "TinyBitSerious",
    "text": "2346",
    "timestamp": 1746863979803
  },
  {
    "user": "TinyBitSerious",
    "text": "23",
    "timestamp": 1746863979986
  },
  {
    "user": "TinyBitSerious",
    "text": "6",
    "timestamp": 1746863980162
  },
  {
    "user": "TinyBitSerious",
    "text": "2346",
    "timestamp": 1746863980346
  },
  {
    "user": "TinyBitSerious",
    "text": "23",
    "timestamp": 1746863980549
  },
  {
    "user": "TinyBitSerious",
    "text": "64234623624346",
    "timestamp": 1746863981391
  },
  {
    "user": "TinyBitSerious",
    "text": "2346",
    "timestamp": 1746863981956
  },
  {
    "user": "TinyBitSerious",
    "text": "wda",
    "timestamp": 1746864216826
  },
  {
    "user": "TinyBitSerious",
    "text": "hi",
    "timestamp": 1746864219516
  },
  {
    "user": "TinyBitSerious",
    "text": "ads",
    "timestamp": 1746864435953
  },
  {
    "user": "TinyBitSerious",
    "text": "hi",
    "timestamp": 1746864780447
  }
]